{"nodes": [{"id": "datamodel_species_entity", "label": "Entite Species (Fiche Espece JSON)", "file_type": "document", "source_file": "docs/04-data-model.md", "source_location": null, "source_url": null, "captured_at": null, "author": null, "contributor": null, "rationale": "Stockage JSON statique choisi pour la faible volumetrie (50 fiches), pas de mises a jour frequentes, deploiement simplifie, versionnable en Git."}, {"id": "datamodel_trait_entity", "label": "Entite Trait (Caractere Discriminant)", "file_type": "document", "source_file": "docs/04-data-model.md", "source_location": null, "source_url": null, "captured_at": null, "author": null, "contributor": null}, {"id": "datamodel_notebook_entry", "label": "Entite NotebookEntry (Carnet Local)", "file_type": "document", "source_file": "docs/04-data-model.md", "source_location": null, "source_url": null, "captured_at": null, "author": null, "contributor": null}, {"id": "datamodel_species_schema_json", "label": "species.schema.json (JSON Schema Draft 2020-12)", "file_type": "document", "source_file": "docs/04-data-model.md", "source_location": null, "source_url": null, "captured_at": null, "author": null, "contributor": null}, {"id": "datamodel_trait_frequency", "label": "traitFrequencyInSpecies (always/usually/sometimes)", "file_type": "document", "source_file": "docs/04-data-model.md", "source_location": null, "source_url": null, "captured_at": null, "author": null, "contributor": null}, {"id": "datamodel_trait_rarity", "label": "traitRarityAmongTrees (unique/rare/common)", "file_type": "document", "source_file": "docs/04-data-model.md", "source_location": null, "source_url": null, "captured_at": null, "author": null, "contributor": null}, {"id": "datamodel_discriminant_power", "label": "discriminantPower (signature/strong/moderate/weak)", "file_type": "document", "source_file": "docs/04-data-model.md", "source_location": null, "source_url": null, "captured_at": null, "author": null, "contributor": null}], "edges": [{"source": "datamodel_species_entity", "target": "datamodel_trait_entity", "relation": "references", "confidence": "EXTRACTED", "confidence_score": 1.0, "source_file": "docs/04-data-model.md", "source_location": null, "weight": 1.0}, {"source": "datamodel_trait_entity", "target": "datamodel_trait_frequency", "relation": "references", "confidence": "EXTRACTED", "confidence_score": 1.0, "source_file": "docs/04-data-model.md", "source_location": null, "weight": 1.0}, {"source": "datamodel_trait_entity", "target": "datamodel_trait_rarity", "relation": "references", "confidence": "EXTRACTED", "confidence_score": 1.0, "source_file": "docs/04-data-model.md", "source_location": null, "weight": 1.0}, {"source": "datamodel_trait_entity", "target": "datamodel_discriminant_power", "relation": "references", "confidence": "EXTRACTED", "confidence_score": 1.0, "source_file": "docs/04-data-model.md", "source_location": null, "weight": 1.0}, {"source": "datamodel_species_entity", "target": "datamodel_species_schema_json", "relation": "implements", "confidence": "EXTRACTED", "confidence_score": 1.0, "source_file": "docs/04-data-model.md", "source_location": null, "weight": 1.0}, {"source": "datamodel_notebook_entry", "target": "arch_localstorage_indexeddb", "relation": "implements", "confidence": "EXTRACTED", "confidence_score": 1.0, "source_file": "docs/04-data-model.md", "source_location": null, "weight": 1.0}, {"source": "datamodel_trait_frequency", "target": "methodology_bayesian_engine", "relation": "references", "confidence": "EXTRACTED", "confidence_score": 1.0, "source_file": "docs/04-data-model.md", "source_location": null, "weight": 1.0}, {"source": "datamodel_trait_rarity", "target": "methodology_bayesian_engine", "relation": "references", "confidence": "EXTRACTED", "confidence_score": 1.0, "source_file": "docs/04-data-model.md", "source_location": null, "weight": 1.0}], "hyperedges": []}